.devcontainer/devcontainer.json
.github/ISSUE_TEMPLATE/bug_report.yml
.github/ISSUE_TEMPLATE/config.yml
.github/ISSUE_TEMPLATE/documentation.yml
.github/ISSUE_TEMPLATE/feature_request.yml
.github/codecov.yml
.github/workflows/_test.yml
.github/workflows/create-tag.yml
.github/workflows/full-tests.yml
.github/workflows/latest-deps-tests.yml
.github/workflows/lint.yml
.github/workflows/pr-tests-skip.yml
.github/workflows/pr-tests.yml
.github/workflows/publish-pypi-approval.yml
.github/workflows/publish-wheel.yml
.github/workflows/release.yml
.github/workflows/test-and-build-wheel.yml
.github/workflows/test-docker.yml
.github/workflows/test-published-dist.yml
.gitlab-ci.yml
.venv/lib/python3.11/site-packages/pip/_vendor/cachecontrol/LICENSE.txt
.venv/lib/python3.11/site-packages/pip/_vendor/dependency_groups/LICENSE.txt
.venv/lib/python3.11/site-packages/pip/_vendor/distlib/LICENSE.txt
.venv/lib/python3.11/site-packages/pip/_vendor/urllib3/LICENSE.txt
.venv/lib/python3.11/site-packages/pip/_vendor/vendor.txt
.venv/lib/python3.11/site-packages/pip-25.3.dist-info/entry_points.txt
.venv/lib/python3.11/site-packages/pip-25.3.dist-info/licenses/AUTHORS.txt
.venv/lib/python3.11/site-packages/pip-25.3.dist-info/licenses/LICENSE.txt
.venv/lib/python3.11/site-packages/pip-25.3.dist-info/licenses/src/pip/_vendor/cachecontrol/LICENSE.txt
.venv/lib/python3.11/site-packages/pip-25.3.dist-info/licenses/src/pip/_vendor/dependency_groups/LICENSE.txt
.venv/lib/python3.11/site-packages/pip-25.3.dist-info/licenses/src/pip/_vendor/distlib/LICENSE.txt
.venv/lib/python3.11/site-packages/pip-25.3.dist-info/licenses/src/pip/_vendor/urllib3/LICENSE.txt
.venv/lib/python3.11/site-packages/pkg_resources/api_tests.txt
.venv/lib/python3.11/site-packages/pkg_resources/tests/data/my-test-package_unpacked-egg/my_test_package-1.0-py3.7.egg/EGG-INFO/SOURCES.txt
.venv/lib/python3.11/site-packages/pkg_resources/tests/data/my-test-package_unpacked-egg/my_test_package-1.0-py3.7.egg/EGG-INFO/dependency_links.txt
.venv/lib/python3.11/site-packages/pkg_resources/tests/data/my-test-package_unpacked-egg/my_test_package-1.0-py3.7.egg/EGG-INFO/top_level.txt
.venv/lib/python3.11/site-packages/setuptools/_vendor/autocommand-2.2.2.dist-info/top_level.txt
.venv/lib/python3.11/site-packages/setuptools/_vendor/backports.tarfile-1.2.0.dist-info/top_level.txt
.venv/lib/python3.11/site-packages/setuptools/_vendor/importlib_metadata-8.0.0.dist-info/top_level.txt
.venv/lib/python3.11/site-packages/setuptools/_vendor/inflect-7.3.1.dist-info/top_level.txt
.venv/lib/python3.11/site-packages/setuptools/_vendor/jaraco/text/Lorem ipsum.txt
.venv/lib/python3.11/site-packages/setuptools/_vendor/jaraco.collections-5.1.0.dist-info/top_level.txt
.venv/lib/python3.11/site-packages/setuptools/_vendor/jaraco.context-5.3.0.dist-info/top_level.txt
.venv/lib/python3.11/site-packages/setuptools/_vendor/jaraco.functools-4.0.1.dist-info/top_level.txt
.venv/lib/python3.11/site-packages/setuptools/_vendor/jaraco.text-3.12.1.dist-info/top_level.txt
.venv/lib/python3.11/site-packages/setuptools/_vendor/typeguard-4.3.0.dist-info/entry_points.txt
.venv/lib/python3.11/site-packages/setuptools/_vendor/typeguard-4.3.0.dist-info/top_level.txt
.venv/lib/python3.11/site-packages/setuptools/_vendor/wheel/vendored/vendor.txt
.venv/lib/python3.11/site-packages/setuptools/_vendor/wheel-0.45.1.dist-info/LICENSE.txt
.venv/lib/python3.11/site-packages/setuptools/_vendor/wheel-0.45.1.dist-info/entry_points.txt
.venv/lib/python3.11/site-packages/setuptools/_vendor/zipp-3.19.2.dist-info/top_level.txt
.venv/lib/python3.11/site-packages/setuptools/config/distutils.schema.json
.venv/lib/python3.11/site-packages/setuptools/config/setuptools.schema.json
.venv/lib/python3.11/site-packages/setuptools/tests/config/setupcfg_examples.txt
.venv/lib/python3.11/site-packages/setuptools-80.9.0.dist-info/entry_points.txt
.venv/lib/python3.11/site-packages/setuptools-80.9.0.dist-info/top_level.txt
.vscode/extensions.json
.vscode/launch.json
.vscode/settings.json
.vscode/tasks.json
LICENSE-Apache-2.0.txt
LICENSE.md
chat-ui/README.md
chat-ui/frontend/404.html
chat-ui/frontend/_next/data/c_3yGnIXISqv9z1fDmxxC/index.json
chat-ui/frontend/_next/static/c_3yGnIXISqv9z1fDmxxC/_buildManifest.js
chat-ui/frontend/_next/static/c_3yGnIXISqv9z1fDmxxC/_ssgManifest.js
chat-ui/frontend/_next/static/chunks/105-4bc220fcbf235939.js
chat-ui/frontend/_next/static/chunks/542b50fd-07ebedc579cef971.js
nemoguardrails-0.19.0.dist-info/LICENCES-3rd-party
nemoguardrails-0.19.0.dist-info/LICENSE-Apache-2.0.txt
nemoguardrails-0.19.0.dist-info/LICENSE.md
nemoguardrails-0.19.0.dist-info/METADATA
nemoguardrails-0.19.0.dist-info/WHEEL
nemoguardrails-0.19.0.dist-info/entry_points.txt
nemoguardrails-0.19.0.dist-info/RECORD
