Metadata-Version: 2.1
Name: nemoguardrails
Version: 0.19.0
Summary: NeMo Guardrails is an open-source toolkit for easily adding programmable guardrails to LLM-based conversational systems.
License: LICENSE.md
Author: NVIDIA
Author-email: nemoguardrails@nvidia.com
Requires-Python: >=3.10,<3.14
Classifier: Development Status :: 4 - Beta
Classifier: Intended Audience :: Developers
Classifier: License :: OSI Approved :: Apache Software License
Classifier: License :: Other/Proprietary License
Classifier: Programming Language :: Python :: 3
Classifier: Programming Language :: Python :: 3.10
Classifier: Programming Language :: Python :: 3.11
Classifier: Programming Language :: Python :: 3.12
Classifier: Programming Language :: Python :: 3.13
Provides-Extra: all
Provides-Extra: eval
Provides-Extra: gcp
Provides-Extra: jailbreak
Provides-Extra: nvidia
Provides-Extra: openai
Provides-Extra: sdd
Provides-Extra: tracing
Requires-Dist: aiofiles (>=24.1.0) ; extra == "tracing" or extra == "all"
Requires-Dist: aiohttp (>=3.10.11)
Requires-Dist: annoy (>=1.17.3)
Requires-Dist: fastapi (>=0.103.0)
Requires-Dist: fastembed (>=0.2.2,<=0.6.0) ; python_version >= "3.10" and python_version < "3.14"
Requires-Dist: google-cloud-language (>=2.14.0) ; extra == "gcp" or extra == "all"
Requires-Dist: httpx (>=0.24.1)
Requires-Dist: jinja2 (>=3.1.6)
Requires-Dist: langchain (>=0.2.14,<2.0.0)
Requires-Dist: langchain-community (>=0.2.5,<2.0.0)
Requires-Dist: langchain-core (>=0.2.14,<2.0.0)
Requires-Dist: langchain-nvidia-ai-endpoints (>=0.2.0) ; extra == "nvidia" or extra == "all"
Requires-Dist: langchain-openai (>=0.1.0) ; extra == "openai" or extra == "all"
Requires-Dist: lark (>=1.1.7)
Requires-Dist: nest-asyncio (>=1.5.6)
Requires-Dist: numpy (>=1.21) ; (python_version >= "3.10" and python_version < "3.12") and (extra == "eval" or extra == "all")
Requires-Dist: numpy (>=1.21,<2.1.0) ; (python_version < "3.10") and (extra == "eval" or extra == "all")
Requires-Dist: numpy (>=1.26) ; (python_version >= "3.12" and python_version < "3.13") and (extra == "eval" or extra == "all")
Requires-Dist: numpy (>=2.1.0) ; (python_version >= "3.13") and (extra == "eval" or extra == "all")
Requires-Dist: opentelemetry-api (>=1.27.0,<2.0.0) ; extra == "tracing" or extra == "all"
Requires-Dist: pandas (>=1.4.0,<3)
Requires-Dist: presidio-analyzer (>=2.2) ; (python_version < "3.13") and (extra == "sdd" or extra == "all")
Requires-Dist: presidio-anonymizer (>=2.2) ; (python_version < "3.13") and (extra == "sdd" or extra == "all")
Requires-Dist: prompt-toolkit (>=3.0)
Requires-Dist: protobuf (>=5.29.5)
Requires-Dist: pydantic (>=1.10)
Requires-Dist: pyyaml (>=6.0)
Requires-Dist: rich (>=13.5.2)
Requires-Dist: simpleeval (>=0.9.13)
Requires-Dist: starlette (>=0.49.1)
Requires-Dist: streamlit (>=1.37.0,<2.0.0) ; (python_version >= "3.10" and python_version < "3.14") and (extra == "eval" or extra == "all")
Requires-Dist: tornado (>=6.5.0) ; (python_version >= "3.10" and python_version < "3.14") and (extra == "eval")
Requires-Dist: tqdm (>=4.65,<5.0) ; extra == "eval" or extra == "all"
Requires-Dist: typer (>=0.8)
Requires-Dist: uvicorn (>=0.23)
Requires-Dist: watchdog (>=3.0.0)
Requires-Dist: yara-python (>=4.5.1,<5.0.0) ; extra == "jailbreak" or extra == "all"
Project-URL: changelog, https://github.com/NVIDIA/NeMo-Guardrails/blob/develop/CHANGELOG.md
Project-URL: documentation, https://docs.nvidia.com/nemo/guardrails/
Project-URL: homepage, https://github.com/NVIDIA/nemo-guardrails
Project-URL: issues, https://github.com/NVIDIA/nemo-guardrails/issues
Project-URL: repository, https://github.com/NVIDIA/NeMo-Guardrails
